{
    "version": "1.47.5",
    "description": "Hearthstone Deck Tracker is an automatic deck tracker and deck manager for Hearthstone.",
    "homepage": "https://hsreplay.net/",
    "license": "Freeware",
    "url": "https://github.com/HearthSim/Hearthstone-Deck-Tracker/releases/download/v1.47.5/Hearthstone.Deck.Tracker-v1.47.5.zip",
    "hash": "57ff0786aec11acba9555546921f0c3a8ed3be07a3ff63ada5420159c7e6b7bc",
    "bin": "Hearthstone Deck Tracker.exe",
    "extract_dir": "Hearthstone Deck Tracker",
    "shortcuts": [
        [
            "Hearthstone Deck Tracker.exe",
            "Hearthstone Deck Tracker"
        ]
    ],
    "persist": "Plugins",
    "checkver": {
        "github": "https://github.com/HearthSim/Hearthstone-Deck-Tracker"
    },
    "autoupdate": {
        "url": "https://github.com/HearthSim/Hearthstone-Deck-Tracker/releases/download/v$version/Hearthstone.Deck.Tracker-v$version.zip"
    }
}
